[
  {
    "digital_object_id": "608873",
    "map_number": "6330-1",
    "title": "Vietnam Center&Sam Johnson Vietnam Archive",
    "provinces": [
      "Saigon",
      "Gia Dinh"
    ],
    "coords": {
      "north": 11.0,
      "south": 10.75,
      "west": 106.75,
      "east": 107.0
    },
    "jpg_url": "https://vva.vietnam.ttu.edu/images.php?img=/maps/Big/6330-1.jpg",
    "ia_identifier": "vma-l7014-63301",
    "iiif_url": "https://iiif.archive.org/image/iiif/2/vma-l7014-63301%2F6330-1.jpg/info.json",
    "allmaps_id": null,
    "annotation_file": "l7014_data/annotations/6330-1.json",
    "annotation_url": "https://trioykjhhwrruwjsklfo.supabase.co/storage/v1/object/public/annotations/6330-1.json"
  },
  {
    "digital_object_id": "608874",
    "map_number": "6330-2",
    "title": "Vietnam Center&Sam Johnson Vietnam Archive",
    "provinces": [
      "Saigon",
      "Gia Dinh"
    ],
    "coords": {
      "north": 10.75,
      "south": 10.5,
      "west": 106.75,
      "east": 107.0
    },
    "jpg_url": "https://vva.vietnam.ttu.edu/images.php?img=/maps/Big/6330-2.jpg",
    "ia_identifier": "vma-l7014-63302",
    "iiif_url": "https://iiif.archive.org/image/iiif/2/vma-l7014-63302%2F6330-2.jpg/info.json",
    "allmaps_id": null,
    "annotation_file": "l7014_data/annotations/6330-2.json",
    "annotation_url": "https://trioykjhhwrruwjsklfo.supabase.co/storage/v1/object/public/annotations/6330-2.json"
  },
  {
    "digital_object_id": "608875",
    "map_number": "6330-3",
    "title": "Vietnam Center&Sam Johnson Vietnam Archive",
    "provinces": [
      "Saigon",
      "Gia Dinh"
    ],
    "coords": {
      "north": 10.75,
      "south": 10.5,
      "west": 106.5,
      "east": 106.75
    },
    "jpg_url": "https://vva.vietnam.ttu.edu/images.php?img=/maps/Big/6330-3.jpg",
    "ia_identifier": "vma-l7014-63303",
    "iiif_url": "https://iiif.archive.org/image/iiif/2/vma-l7014-63303%2F6330-3.jpg/info.json",
    "allmaps_id": null,
    "annotation_file": "l7014_data/annotations/6330-3.json",
    "annotation_url": "https://trioykjhhwrruwjsklfo.supabase.co/storage/v1/object/public/annotations/6330-3.json"
  },
  {
    "digital_object_id": "608876",
    "map_number": "6330-4",
    "title": "Vietnam Center&Sam Johnson Vietnam Archive",
    "provinces": [
      "Saigon",
      "Gia Dinh"
    ],
    "coords": {
      "north": 11.0,
      "south": 10.75,
      "west": 106.5,
      "east": 106.75
    },
    "jpg_url": "https://vva.vietnam.ttu.edu/images.php?img=/maps/Big/6330-4.jpg",
    "ia_identifier": "vma-l7014-63304",
    "iiif_url": "https://iiif.archive.org/image/iiif/2/vma-l7014-63304%2F6330-4.jpg/info.json",
    "allmaps_id": null,
    "annotation_file": "l7014_data/annotations/6330-4.json",
    "annotation_url": "https://trioykjhhwrruwjsklfo.supabase.co/storage/v1/object/public/annotations/6330-4.json"
  },
  {
    "digital_object_id": "608869",
    "map_number": "6329-1",
    "title": "Vietnam Center&Sam Johnson Vietnam Archive",
    "provinces": [
      "Gia Dinh"
    ],
    "coords": {
      "north": 10.5,
      "south": 10.25,
      "west": 106.75,
      "east": 107.0
    },
    "jpg_url": "https://vva.vietnam.ttu.edu/images.php?img=/maps/Big/6329-1.jpg",
    "ia_identifier": "vma-l7014-63291",
    "iiif_url": "https://iiif.archive.org/image/iiif/2/vma-l7014-63291%2F6329-1.jpg/info.json",
    "allmaps_id": null,
    "annotation_file": "l7014_data/annotations/6329-1.json",
    "annotation_url": "https://trioykjhhwrruwjsklfo.supabase.co/storage/v1/object/public/annotations/6329-1.json"
  },
  {
    "digital_object_id": "608872",
    "map_number": "6329-4",
    "title": "Vietnam Center&Sam Johnson Vietnam Archive",
    "provinces": [
      "Gia Dinh"
    ],
    "coords": {
      "north": 10.5,
      "south": 10.25,
      "west": 106.5,
      "east": 106.75
    },
    "jpg_url": "https://vva.vietnam.ttu.edu/images.php?img=/maps/Big/6329-4.jpg",
    "ia_identifier": null,
    "iiif_url": null,
    "allmaps_id": null
  },
  {
    "digital_object_id": "608921",
    "map_number": "6429-4",
    "title": "Vietnam Center&Sam Johnson Vietnam Archive",
    "provinces": [
      "Gia Dinh"
    ],
    "coords": {
      "north": 10.5,
      "south": 10.25,
      "west": 107.0,
      "east": 107.25
    },
    "jpg_url": "https://vva.vietnam.ttu.edu/images.php?img=/maps/Big/6429-4.jpg",
    "ia_identifier": null,
    "iiif_url": null,
    "allmaps_id": null
  },
  {
    "digital_object_id": "608924",
    "map_number": "6430-3",
    "title": "Vietnam Center&Sam Johnson Vietnam Archive",
    "provinces": [
      "Gia Dinh"
    ],
    "coords": {
      "north": 10.75,
      "south": 10.5,
      "west": 107.0,
      "east": 107.25
    },
    "jpg_url": "https://vva.vietnam.ttu.edu/images.php?img=/maps/Big/6430-3.jpg",
    "ia_identifier": null,
    "iiif_url": null,
    "allmaps_id": null
  }
]